todo_txt_tui/__init__.py
todo_txt_tui/core.py
todo_txt_tui-0.2.7.dist-info/METADATA
todo_txt_tui-0.2.7.dist-info/WHEEL
todo_txt_tui-0.2.7.dist-info/entry_points.txt
todo_txt_tui-0.2.7.dist-info/top_level.txt
todo_txt_tui-0.2.7.dist-info/RECORD
