Metadata-Version: 2.1
Name: todo-txt-tui
Version: 0.2.7
Summary: A powerful, keyboard-driven terminal application for managing todo.txt files.
Author: mdillondc
Requires-Dist: urwid
Requires-Dist: python-dateutil
Requires-Dist: aiohttp
